setup.py
dropstar/__init__.py
dropstar/httpd.py
dropstar/process.py
dropstar.egg-info/PKG-INFO
dropstar.egg-info/SOURCES.txt
dropstar.egg-info/dependency_links.txt
dropstar.egg-info/requires.txt
dropstar.egg-info/top_level.txt