Metadata-Version: 1.0
Name: dropstar
Version: 2010.10.14.0
Summary: dropSTAR: Drop Scripts, Templates and RPC.  A stand-alone HTTP server for mixing dynamic and static content with RPC calls.  Focused on system administration and automation tasks.
Home-page: http://ge01f.com/demo/monitor/
Author: Geoff Howland
Author-email: geoff@gmail.com
License: MIT
Keywords: httpd rpc http json templating web server
Platform: UNKNOWN
Classifier: Development Status :: 4 - Beta
Classifier: Environment :: Web Environment
Classifier: Intended Audience :: Developers
Classifier: Intended Audience :: Information Technology
Classifier: Intended Audience :: System Administrators
Classifier: License :: OSI Approved :: MIT License
Classifier: Natural Language :: English
Classifier: Operating System :: MacOS :: MacOS X
Classifier: Operating System :: POSIX :: BSD :: FreeBSD
Classifier: Operating System :: POSIX :: Linux
Classifier: Programming Language :: Python :: 2.6
Classifier: Topic :: System :: Systems Administration
Classifier: Topic :: Internet :: WWW/HTTP
Classifier: Topic :: Internet :: WWW/HTTP :: HTTP Servers
Classifier: Topic :: Internet :: WWW/HTTP :: Dynamic Content
